blitzkrieg/__init__.py
blitzkrieg/alembic_manager.py
blitzkrieg/blitz_env_manager.py
blitzkrieg/class_instances/blitz_env_manager.py
blitzkrieg/class_instances/docker_manager.py
blitzkrieg/cli/main.py
blitzkrieg/cookie_cutter_manager.py
blitzkrieg/database_manager.py
blitzkrieg/db/__init__.py
blitzkrieg/db/models/__init__.py
blitzkrieg/db/models/base.py
blitzkrieg/db/models/cli_command.py
blitzkrieg/db/models/environment_variable.py
blitzkrieg/db/models/feature.py
blitzkrieg/db/models/issue.py
blitzkrieg/db/models/metric.py
blitzkrieg/db/models/project.py
blitzkrieg/db/models/software_asset.py
blitzkrieg/db/models/workspace.py
blitzkrieg/docker_manager.py
blitzkrieg/enums/__init__.py
blitzkrieg/enums/project_types_enum.py
blitzkrieg/file_manager.py
blitzkrieg/file_writers/base_docker_compose_writer.py
blitzkrieg/file_writers/base_dockerfile_writer.py
blitzkrieg/file_writers/workspace_docker_compose_writer.py
blitzkrieg/file_writers/workspace_dockerfile_writer.py
blitzkrieg/init_rust_ext.sh
blitzkrieg/pgadmin_manager.py
blitzkrieg/postgres_manager.py
blitzkrieg/project_management/db/connection.py
blitzkrieg/project_management/db/enums/project_management/deployment_type_enum.py
blitzkrieg/project_management/db/models/Base.py
blitzkrieg/project_management/db/models/deployment.py
blitzkrieg/project_management/db/models/document.py
blitzkrieg/project_management/db/models/document_type.py
blitzkrieg/project_management/db/models/issue.py
blitzkrieg/project_management/db/models/pipeline.py
blitzkrieg/project_management/db/models/project.py
blitzkrieg/project_management/db/models/task.py
blitzkrieg/rust_codetextualizer/.github/workflows/CI.yml
blitzkrieg/rust_codetextualizer/.gitignore
blitzkrieg/rust_codetextualizer/Cargo.lock
blitzkrieg/rust_codetextualizer/Cargo.toml
blitzkrieg/rust_codetextualizer/pyproject.toml
blitzkrieg/rust_codetextualizer/rebuild.sh
blitzkrieg/rust_codetextualizer/src/lib.rs
blitzkrieg/templates/poetry-cli-template/cookiecutter.json
blitzkrieg-0.3.43.dist-info/METADATA
blitzkrieg-0.3.43.dist-info/WHEEL
blitzkrieg-0.3.43.dist-info/entry_points.txt
blitzkrieg-0.3.43.dist-info/RECORD
