Metadata-Version: 2.1
Name: blitzkrieg
Version: 0.3.43
Summary: A tool for rapid project setup and management
Author: cybrvybe
Author-email: alexfigueroa.cybr@gmail.com
Requires-Python: >=3.11,<4.0
Classifier: Programming Language :: Python :: 3
Classifier: Programming Language :: Python :: 3.11
Classifier: Programming Language :: Python :: 3.12
Requires-Dist: SQLAlchemy (>=2.0.25,<3.0.0)
Requires-Dist: alembic (>=1.13.1,<2.0.0)
Requires-Dist: click (>=8.1.7,<9.0.0)
Requires-Dist: colorama (>=0.4.6,<0.5.0)
Requires-Dist: loguru (>=0.7.2,<0.8.0)
Requires-Dist: psycopg2-binary (>=2.9.9,<3.0.0)
Requires-Dist: pyfiglet (>=1.0.2,<2.0.0)
Requires-Dist: python-dotenv (>=1.0.1,<2.0.0)
Requires-Dist: questionary (>=2.0.1,<3.0.0)
